LICENSE
README.md
runtime_type_checker/__init__.py
runtime_type_checker/_checkers.py
runtime_type_checker/typing_inspect_extensions.py
runtime_type_checker/utils.py
runtime_type_checker-0.6.0.dist-info/LICENSE
runtime_type_checker-0.6.0.dist-info/METADATA
runtime_type_checker-0.6.0.dist-info/WHEEL
runtime_type_checker-0.6.0.dist-info/RECORD
