Metadata-Version: 2.1
Name: runtime-type-checker
Version: 0.6.0
Summary: Runtime-type-checker performs type check at runtime with help of type annotations
Home-page: https://github.com/pjcampi/runtime-type-checker
License: MIT
Author: PJCampi
Author-email: pierrejean.campigotto@gmail.com
Requires-Python: >=3.6.1,<4.0.0
Classifier: License :: OSI Approved :: MIT License
Classifier: Natural Language :: English
Classifier: Programming Language :: Python :: 3
Classifier: Programming Language :: Python :: 3.7
Classifier: Programming Language :: Python :: 3.8
Classifier: Programming Language :: Python :: 3.9
Classifier: Programming Language :: Python :: 3.10
Classifier: Programming Language :: Python :: 3.11
Classifier: Programming Language :: Python :: 3.12
Classifier: Programming Language :: Python :: 3.6
Requires-Dist: dataclasses (==0.7) ; python_version >= "3.6" and python_version < "3.7"
Requires-Dist: typing_inspect (>=0.9.0,<0.10.0)
Project-URL: Repository, https://github.com/pjcampi/runtime-type-checker
